Workbook

Sheet Instrucciones
A1: MEMGD — Matriz de Evaluación del Modelo de Evaluación de Madurez en Gobierno y Gestión de Datos
A2: Versión 1.1 — para las entidades públicas
A4: Instrucciones de uso
A5: 1. En la hoja "Matriz de Evaluación", revise cada una de las 75 preguntas junto con sus 6 opciones de respuesta (niveles 0 a 5).
A6: 2. En la columna "Respuesta" (celda resaltada en amarillo), seleccione el nivel (0 a 5) que mejor describe el estado actual de la entidad para esa pregunta, según la lista desplegable de la celda.
A7: 3. Cuatro preguntas (3.16, 6.8, 8.2 y 8.4) admiten la respuesta "NA" (No Aplica), únicamente cuando se cumple la condición objetiva y verificable indicada en su columna "¿Admite No Aplica?". Su uso debe sustentarse en un análisis documentado por la entidad evaluada y queda sujeto a revisión por el evaluador — no es una autocalificación libre.
A8: 4. Use las columnas "Explicación" y "Resultados Esperados / Ejemplos" como referencia para interpretar cada pregunta y el criterio que se espera en el nivel más alto (5).
A9: 5. La hoja "Hoja de Puntajes" calcula automáticamente, mediante fórmulas, el promedio de cada una de las 8 dimensiones (excluyendo del denominador las preguntas sin responder y las marcadas "NA") y el Puntaje Final del MEMGD (promedio de los 8 promedios de dimensión), con su nivel de madurez correspondiente. El nivel corresponde a la parte entera del puntaje (p. ej., 2,9 = nivel 2; el nivel 3 se alcanza con 3,0 o más).
A10: 6. Esta Matriz es la modalidad de aplicación manual (offline) del MEMGD. Sus resultados se registran en la plataforma del Centro Nacional de Datos (madurez.cnd.gob.pe), y el nivel de madurez institucional se acredita con el informe final validado y aprobado por el CND.
A12: Escala de madurez (alineada a la nomenclatura oficial de la ENGD 2026-2030, RM N.° 049-2026-PCM)
A14: Nivel | B14: Nombre oficial (ENGD / MEMGD)
A15: 0 | B15: No iniciado
A16: 1 | B16: Inicial
A17: 2 | B17: En desarrollo
A18: 3 | B18: Definido
A19: 4 | B19: Logrado
A20: 5 | B20: Optimizado
A22: Nota: documente el sustento de cada respuesta en el Inventario de Evidencias, conforme a las secciones 4 y 5 del Modelo (Metodología de la Evaluación y Metodología de Puntuación).

Sheet Matriz de Evaluación
A1: Dimensión | B1: N° | C1: Título | D1: Pregunta | E1: Opción 0 | F1: Opción 1 | G1: Opción 2 | H1: Opción 3 | I1: Opción 4 | J1: Opción 5 | K1: ¿Admite "No Aplica"? | L1: Respuesta (0-5 o NA) | M1: Explicación | N1: Resultados Esperados / Ejemplos
A2: D1. ESTRATEGIA DE GOBIERNO DE DATOS | B2: 1.1 | C2: Formulación y aprobación del PAGD | D2: ¿En qué etapa se encuentra la formulación y aprobación del Plan de Acción de Gobierno de Datos (PAGD)? | E2: No existe gestión estratégica de datos, ni formal ni informal. | F2: Existe una visión u objetivos reconocidos informalmente, sin documentación ni PAGD. | G2: El PAGD está en borrador, con algunos elementos definidos (visión, misión, beneficios u objetivos), aún no aprobado. | H2: El PAGD ha sido formalmente aprobado por el Comité de Gobierno y Transformación Digital. | I2: La implementación del PAGD se supervisa mediante revisiones periódicas que verifican su vigencia. | J2: El PAGD es un pilar de la gestión estratégica institucional, revisado y optimizado de forma continua. | K2: No | M2: Evalúa la formulación y aprobación formal del Plan de Acción de Gobierno de Datos (PAGD) —instrumento único exigido por la ENGD (RM 049-2026-PCM, Art. 4.4-5.2)—, en su dimensión puramente procedimental (etapa de formulación y aprobación). La articulación de su enfoque estratégico con los Objetivos Estratégicos Institucionales (OEI) se evalúa por separado en la pregunta 1.2. | N2: Se espera un PAGD formalmente aprobado por el Comité de Gobierno y Transformación Digital, revisado y optimizado de forma continua. La mejora implica llevar el PAGD de un borrador a su aprobación formal, y mantener esa vigencia con revisiones periódicas. Ejemplo: El Comité aprueba mediante acta el PAGD en su sesión ordinaria, y programa una revisión semestral de vigencia.
A3: D1. ESTRATEGIA DE GOBIERNO DE DATOS | B3: 1.2 | C3: Articulación estratégica del PAGD con los OEI | D3: ¿En qué medida el enfoque estratégico del PAGD está articulado con los Objetivos Estratégicos Institucionales (OEI) de la entidad? | E3: No hay ninguna referencia a los OEI en la gestión de datos. | F3: Se reconoce la necesidad de alinear con los OEI, sin vinculación explícita. | G3: Existe una vinculación general o declarativa con los OEI, sin trazabilidad concreta a objetivos específicos. | H3: El PAGD articula explícitamente su visión, misión, beneficios y objetivos con OEI específicos. | I3: La articulación con los OEI se revisa periódicamente para verificar su vigencia. | J3: La articulación con los OEI es un criterio activo que orienta la priorización y ajuste continuo del PAGD. | K3: No | M3: Evalúa si el enfoque estratégico del PAGD (visión, misión, beneficios, objetivos) está articulado con los Objetivos Estratégicos Institucionales (OEI) de la entidad — distinta de la formulación y aprobación procedimental del PAGD, evaluada en 1.1. | N3: Se espera que la articulación con los OEI sea un criterio activo que oriente la priorización y ajuste continuo del PAGD. La mejora implica pasar de una vinculación declarativa a una trazabilidad concreta con objetivos específicos. Ejemplo: El PAGD incluye una matriz que vincula cada una de sus iniciativas con el OEI institucional al que contribuye.
A4: D1. ESTRATEGIA DE GOBIERNO DE DATOS | B4: 1.3 | C4: Diagnóstico, objetivos e iniciativas priorizadas del PAGD | D4: ¿En qué medida la entidad cuenta con un diagnóstico de su situación de gobierno y gestión de datos, y lo traduce en objetivos específicos con resultados esperados e iniciativas priorizadas con cronograma y responsables? | E4: No existe diagnóstico, objetivos ni iniciativas de datos identificables, ni dentro ni fuera de un PAGD. | F4: Existe una apreciación informal de la situación de datos, o iniciativas aisladas, sin objetivos ni resultados esperados articulados entre sí. | G4: Existe un diagnóstico documentado parcial, u objetivos/iniciativas definidos de forma informal o dispersa — aún no consolidados en un PAGD. | H4: El PAGD formal consolida el diagnóstico, los objetivos específicos con resultados esperados, y las iniciativas priorizadas con cronograma y responsables, conforme al contenido mínimo del Art. 5.1 de la RM 049-2026-PCM. | I4: El diagnóstico, los objetivos y las iniciativas se revisan y actualizan periódicamente, usando el avance de los indicadores (KPI/KRI, ver pregunta 1.4) para verificar el cumplimiento de los resultados esperados. | J4: El PAGD es un instrumento vivo: su diagnóstico e iniciativas se priorizan dinámicamente según el impacto medido de los resultados, retroalimentando el ciclo de planeamiento institucional. | K4: No | M4: Evalúa si la gestión de datos de la entidad —formalizada en el PAGD o, en etapas tempranas, mediante iniciativas informales— cuenta con diagnóstico, objetivos con resultados esperados, e iniciativas priorizadas con cronograma y responsables, conforme al contenido mínimo exigido por el Art. 5.1 de la RM 049-2026-PCM. | N4: Se espera un PAGD como instrumento vivo, con iniciativas priorizadas dinámicamente según impacto y resultados medidos. La mejora implica consolidar en un solo documento el diagnóstico, los objetivos y las iniciativas con su cronograma y responsables (el financiamiento de las iniciativas se evalúa en las preguntas 1.5 y 2.1). Ejemplo: El PAGD incluye una matriz con 8 iniciativas, cada una con responsable y fecha de inicio y fin.
A5: D1. ESTRATEGIA DE GOBIERNO DE DATOS | B5: 1.4 | C5: Definición de indicadores (KPI/KRI) y reporte de avance al Comité y a la SGTD | D5: ¿Se definen indicadores (KPI/KRI) para monitorizar las iniciativas de datos de la entidad, y con qué frecuencia el OGD reporta su avance al Comité de Gobierno y Transformación Digital y a la SGTD? | E5: No se definen indicadores de las iniciativas de datos, ni se reportan avances. | F5: Se identifican indicadores de forma informal para algunas iniciativas de datos, sin uso sistemático ni reporte formal. | G5: Se recopilan indicadores de forma inconsistente; los reportes del OGD (de existir) son esporádicos o no cumplen la frecuencia normativa vigente. | H5: El OGD reporta formalmente los indicadores del PAGD al Comité y a la SGTD con la frecuencia que establece la normativa vigente aplicable. | I5: Los indicadores se analizan activamente y se utilizan para ajustar el PAGD, con revisión periódica de las causas de las desviaciones identificadas. | J5: El reporte del OGD incorpora análisis predictivo y recomendaciones proactivas para la toma de decisiones estratégicas del Comité, anticipando riesgos antes de que afecten el cumplimiento del PAGD. | K5: No | M5: Evalúa si la entidad ha definido indicadores para medir el avance (KPI) y los riesgos (KRI) de sus iniciativas de datos, si los mide y los usa para tomar decisiones, y si el OGD reporta formalmente ese avance al Comité de Gobierno y Transformación Digital y a la SGTD con la frecuencia que exige la normativa vigente. | N5: Se espera que el reporte del OGD incorpore análisis predictivo y recomendaciones proactivas para la toma de decisiones del Comité. La mejora implica definir indicadores claros y establecer el reporte formal con la frecuencia normativa vigente: trimestral para el avance de las acciones estratégicas de la ENGD al Comité y a la SGTD (ENGD, Sección VII), y semestral para el reporte del OGD a la SGTD sobre cumplimiento normativo (RSGTD N° 001-2022-PCM/SGTD). Ejemplo: El OGD presenta periódicamente un tablero con 6 KPI del PAGD (ej. % de iniciativas en curso, % de presupuesto ejecutado) al Comité y remite copia a la SGTD.
A6: D1. ESTRATEGIA DE GOBIERNO DE DATOS | B6: 1.5 | C6: Articulación con PEI/POI/PMI/PGD y aseguramiento presupuestal | D6: ¿En qué grado las iniciativas de datos de la entidad están articuladas con el Plan Estratégico Institucional (PEI), el Plan Operativo Institucional (POI), el Programa Multianual de Inversiones (PMI) y el Plan de Gobierno Digital (PGD), garantizando presupuesto para su ejecución? | E6: Las iniciativas de datos no están incorporadas en el PEI, POI ni PGD —ni, cuando corresponda, en el PMI— ni cuentan con ningún respaldo presupuestal. | F6: Las iniciativas de datos se gestionan de forma aislada, con financiamiento puntual, sin referencia formal en los instrumentos de gestión institucional. | G6: Se está integrando parcialmente el PAGD (o las iniciativas de datos, de existir aún sin PAGD) con el PEI, POI, PMI o PGD, sin asignación presupuestal definida. | H6: El PAGD está formalmente articulado con el PEI, el POI y el PGD de la entidad, y con el PMI cuando sus iniciativas califiquen como proyectos de inversión. | I6: La articulación garantiza presupuesto para la sostenibilidad de las iniciativas del PAGD, administrado en el marco del PGD. | J6: La gestión presupuestal de las iniciativas de datos está optimizada y demuestra contribución medible a los objetivos institucionales. | K6: No | M6: Evalúa si las iniciativas de datos de la entidad están articuladas con los instrumentos de planeamiento institucional (PEI, POI, PMI, PGD), garantizando presupuesto para su ejecución, conforme al Art. 5.2 de la RM 049-2026-PCM. | N6: Se espera una gestión presupuestal optimizada que demuestre contribución medible a los objetivos institucionales. La mejora implica incorporar formalmente los proyectos de datos en el PEI, el POI y el PGD. Para el nivel 3 se requiere la articulación con los tres instrumentos a la vez (no son alternativas entre sí), y con el PMI únicamente cuando las iniciativas califiquen como proyecto de inversión pública. Ejemplo: El proyecto "Implementación del MRD institucional" figura en el POI del área de TI con una partida presupuestal específica para el año fiscal, y está referenciado en el PGD de la entidad.
A7: D1. ESTRATEGIA DE GOBIERNO DE DATOS | B7: 1.6 | C7: Gestión de datos como activo estratégico en la operación diaria | D7: Más allá de la formalización del PAGD, ¿en qué medida se gestionan los datos como un activo estratégico en la operación diaria de la entidad, a lo largo de su ciclo de vida (recopilación, procesamiento, publicación, almacenamiento, disposición), de forma transparente y ética? | E7: No hay conciencia ni procesos para gestionar los datos como activo estratégico en el día a día. | F7: Se reconoce verbalmente la importancia de los datos, pero su gestión operativa es esporádica y reactiva. | G7: Existen prácticas en desarrollo, aplicadas de forma inconsistente entre áreas. | H7: Existen procesos definidos y aplicados de forma consistente, priorizando transparencia y uso ético. | I7: Estos procesos se monitorean y sus resultados se miden periódicamente. | J7: La gestión de datos como activo estratégico está plenamente integrada en la operación institucional. | K7: No | M7: Mide, más allá de la existencia formal del PAGD, si en la operación diaria de la entidad los datos se gestionan efectivamente como un activo estratégico a lo largo de su ciclo de vida (recopilación, procesamiento, publicación, almacenamiento, disposición), priorizando transparencia y uso ético. | N7: Se espera que la gestión de datos como activo estratégico esté plenamente integrada en la operación institucional. La mejora implica que las áreas apliquen prácticas consistentes de gestión del ciclo de vida del dato, no solo lo declarado en el PAGD. Ejemplo: El área de trámites documentales aplica un procedimiento estándar de verificación de datos antes de su publicación, sin que medie instrucción puntual.
A8: D1. ESTRATEGIA DE GOBIERNO DE DATOS | B8: 1.7 | C8: Uso de información para la toma de decisiones | D8: ¿En qué medida la información generada a partir de los datos se utiliza como insumo principal para la toma de decisiones en los procesos de gestión institucional? | E8: Las decisiones se toman por intuición o experiencia, sin datos como insumo principal. | F8: Los datos se usan de forma limitada e informal para decisiones operativas puntuales. | G8: El uso de datos se fomenta en algunas áreas, con informes básicos, sin análisis sistemático transversal. | H8: La entidad cuenta con una práctica establecida de uso de datos para la toma de decisiones en las áreas identificadas como críticas. | I8: Los informes de gestión institucional incorporan datos, análisis de tendencias y proyecciones que respaldan formalmente las decisiones estratégicas. | J8: Las decisiones institucionales se basan sistemáticamente en datos y analítica avanzada, de forma repetible y predecible. | K8: No | M8: Evalúa el grado en que la información generada a partir de datos se utiliza como insumo principal —y no solo referencial— para la toma de decisiones en los procesos de gestión institucional. | N8: Se espera que las decisiones institucionales se basen sistemáticamente en datos y analítica avanzada, de forma repetible y predecible. La mejora implica que los informes de gestión incorporen datos y análisis de tendencias que respalden formalmente las decisiones. Evidencia orientativa por nivel: en el nivel 3, actas o reportes periódicos de las áreas críticas que documenten el uso de datos en sus decisiones; en el nivel 4, informes de gestión institucional con secciones de análisis de datos y tendencias (ejemplo: el informe trimestral de gestión de la Alta Dirección incluye una sección de "Indicadores basados en datos" que sustenta las decisiones de reasignación de recursos); en el nivel 5, tableros de control o modelos analíticos de uso institucionalizado y recurrente, que anteceden la decisión en vez de justificarla después de tomada.
A9: D1. ESTRATEGIA DE GOBIERNO DE DATOS | B9: 1.8 | C9: Frecuencia y uso de las evaluaciones de madurez de gobierno de datos | D9: ¿Con qué frecuencia y profundidad se realizan evaluaciones de madurez de gobierno de datos para identificar brechas y generar planes de acción? | E9: Nunca se han realizado evaluaciones de madurez de gobierno de datos. | F9: Se ha realizado una evaluación exploratoria o puntual, sin seguimiento formal de resultados. | G9: Se están iniciando evaluaciones periódicas, con planes de acción incompletos o inconsistentes. | H9: Se realizan evaluaciones de madurez de forma periódica, generando y ejecutando planes de acción de forma formal. | I9: Las evaluaciones forman parte de un ciclo de mejora continua, con monitoreo del avance de los planes de acción. | J9: Las evaluaciones son proactivas e integradas a la planificación estratégica institucional. | K9: No | M9: Evalúa si la entidad aplica el MEMGD de forma periódica —no como un ejercicio único— y si usa sus resultados: que las brechas identificadas se traduzcan en acciones del PAGD con seguimiento de su ejecución, y que la comparación entre evaluaciones sucesivas permita verificar el avance real. | N9: Se espera que las evaluaciones sean proactivas e integradas a la planificación estratégica institucional. La mejora implica programar evaluaciones periódicas con seguimiento formal de los planes de acción resultantes. Se recomienda metodológicamente una periodicidad de 18 meses entre evaluaciones; esta cadencia es orientativa y no constituye un requisito estricto para calificar en el nivel 3. Ejemplo: La entidad aplica el MEMGD por segunda vez a los 18 meses de la primera evaluación, comparando resultados y actualizando su PAGD en función de las brechas identificadas.
A10: D2. VIABILIDAD FINANCIERA | B10: 2.1 | C10: Asignación y sostenibilidad de recursos y presupuesto para las iniciativas de datos | D10: ¿Qué nivel de asignación de recursos y presupuesto específico se ha logrado para la sostenibilidad de las iniciativas de datos de la entidad? | E10: No se asignan recursos ni presupuesto para las iniciativas de datos. | F10: La asignación de recursos es esporádica, obtenida de fondos generales, sin planificación formal. | G10: Se realizan esfuerzos para asegurar presupuesto a las iniciativas de datos (con o sin PAGD formalizado), pero la asignación no está formalizada ni es sostenible. | H10: Se han identificado y asignado formalmente recursos y presupuesto para las iniciativas de datos de la entidad —incluidas en el PAGD cuando la entidad ya cuente con uno— dentro del presupuesto institucional del año, sea mediante una meta presupuestal propia o como parte identificada de una meta o actividad ya existente. | I10: Se realiza monitoreo continuo de la ejecución presupuestal, asegurando que las iniciativas cumplan sus objetivos financieros. | J10: Los recursos y el presupuesto están completamente optimizados, asegurando la sostenibilidad y el crecimiento de las iniciativas de datos. | K10: No | M10: Evalúa si la entidad asigna recursos y presupuesto específico y sostenible a sus iniciativas de datos, sean estas parte de un PAGD ya formalizado o aún gestionadas de forma informal. | N10: Se espera que los recursos y el presupuesto estén completamente optimizados, asegurando la sostenibilidad y el crecimiento de las iniciativas de datos. La mejora implica pasar de financiamiento esporádico con fondos generales a una asignación formal y específica. Ejemplo: la entidad identifica y asigna un monto específico para "Implementación del Gobierno de Datos" dentro de su presupuesto institucional del año — como meta presupuestal propia en entidades con mayor capacidad de estructuración presupuestal, o como componente identificado dentro de una meta de TI existente en entidades de menor tamaño.
A11: D2. VIABILIDAD FINANCIERA | B11: 2.2 | C11: Participación de las partes interesadas en la justificación presupuestal | D11: ¿En qué grado se ha involucrado a las partes interesadas en la elaboración y justificación del requerimiento presupuestal para la gestión de datos? | E11: Las partes interesadas no participan en la elaboración del presupuesto. | F11: Son notificadas, pero sin participación activa o sistemática. | G11: Algunas son consultadas, pero el involucramiento es limitado. | H11: Las partes interesadas relevantes participan activamente en la elaboración y justificación del presupuesto. | I11: El requerimiento de presupuesto es validado formalmente por las partes interesadas antes de su presentación, incorporando sus observaciones. | J11: La participación es estratégica y continua, promoviendo transparencia en la viabilidad financiera. | K11: No | M11: Evalúa el grado de involucramiento de las partes interesadas (áreas usuarias, TI, planeamiento, alta dirección) en la elaboración y sustento del requerimiento presupuestal para la gestión de datos. | N11: Se espera una participación estratégica y continua que promueva transparencia en la viabilidad financiera. La mejora implica pasar de la mera notificación a la validación activa del requerimiento por las partes interesadas. Ejemplo: El área de Planeamiento y Presupuesto valida formalmente el requerimiento presupuestal de la Oficina de Gobierno de Datos antes de su presentación a la Alta Dirección.
A12: D2. VIABILIDAD FINANCIERA | B12: 2.3 | C12: Justificación de resultados, productos y servicios de las iniciativas de datos | D12: ¿Se han justificado los resultados, productos y/o servicios esperados de las iniciativas de datos de la entidad para garantizar su financiamiento? | E12: No se han justificado los resultados, productos o servicios esperados de las iniciativas de datos. | F12: Se presenta una justificación genérica de alguna iniciativa puntual, sin detalle suficiente. | G12: La justificación de las iniciativas de datos está en proceso, sin resultados/servicios claramente definidos. | H12: Se cuenta con una justificación documentada de resultados, productos y servicios que sustenta el financiamiento de las iniciativas de datos —incluidas en el PAGD cuando la entidad ya cuente con uno—. | I12: Se monitorea el cumplimiento de los resultados, productos y servicios justificados frente a lo planificado, y esa información se usa para ajustar la planificación de recursos. | J12: La justificación es integral y garantiza la disponibilidad financiera a largo plazo, usándose para medir el valor generado. | K12: No | M12: Evalúa si la entidad documenta la justificación de los resultados, productos y/o servicios esperados de sus iniciativas de datos, como sustento para obtener y mantener su financiamiento. | N12: Se espera una justificación integral que garantice la disponibilidad financiera a largo plazo y se use para medir el valor generado. La mejora implica documentar de forma específica (no genérica) los resultados esperados de cada iniciativa. Ejemplo: El expediente técnico del proyecto "Implementación del MDM" incluye una sección de resultados esperados con métricas de reducción de duplicados como sustento de la inversión.
A13: D2. VIABILIDAD FINANCIERA | B13: 2.4 | C13: Metodología de medición del beneficio, utilidad e impacto social de las iniciativas de datos | D13: ¿Se ha establecido una metodología para calcular y monitorear periódicamente el beneficio, utilidad y/o impacto social de las iniciativas de datos de la entidad, y se usa para tomar decisiones? | E13: No se ha establecido ninguna metodología para calcular el beneficio o impacto social de las iniciativas de datos. | F13: Se recopilan datos básicos sobre alguna iniciativa puntual, pero el cálculo del impacto es ad-hoc. | G13: Se está desarrollando una metodología, sin formalizar ni monitorear periódicamente. | H13: Se cuenta con metodología definida para justificar inversiones, midiendo el impacto financiero, utilidad y/o social de las iniciativas de datos. | I13: El beneficio/impacto social se monitorea periódicamente, permitiendo proyectar el retorno de futuras inversiones. | J13: La gestión de recursos es transparente y optimizada, maximizando continuamente el beneficio e impacto social. | K13: No | M13: Evalúa si la entidad ha definido una metodología para calcular y monitorear el beneficio, utilidad o impacto social de sus iniciativas de datos, usando esa información para la toma de decisiones sobre inversión. | N13: Se espera una gestión de recursos transparente y optimizada que maximice continuamente el beneficio e impacto social. La mejora implica definir una metodología formal de medición de impacto, más allá del seguimiento presupuestal básico. Ejemplo: La entidad calcula que la implementación del catálogo de datos abiertos generó un ahorro estimado en tiempo de atención de solicitudes de acceso a la información.
... A76: D8. INTEROPERABILIDAD Y DATOS ABIERTOS | B76: 8.6 | C76: Catálogo de APIs para acceso y consumo masivo de datos | D76: ¿Se cuenta con un catálogo para el acceso y consumo masivo de datos por medio de APIs? | E76: No existe un catálogo de datos para acceso vía APIs. | F76: Se tienen APIs desarrolladas ad-hoc, pero sin un catálogo o documentación de acceso. | G76: Se está desarrollando un catálogo inicial de datos, pero el acceso vía API o su documentación es limitada. | H76: La institución ha creado y mantiene un catálogo organizado que permite el acceso a sus datos a través de APIs. | I76: Se cuenta con documentación clara y completa sobre cómo utilizar las APIs, fomentando el consumo masivo de datos y su reutilización. | J76: Se han implementado APIs RESTful Gubernamentales estandarizadas y seguras, y el catálogo es un pilar para el intercambio de datos entre instituciones y con terceros. | K76: No | M76: Evalúa si la entidad pone sus datos a disposición mediante APIs —interfaces que permiten a otros sistemas consultarlos de forma automatizada— y si estas se organizan en un catálogo que indique qué APIs existen, qué datos ofrecen, cómo acceder a ellas y bajo qué condiciones, de modo que terceros puedan reutilizar los datos sin solicitudes caso por caso. Se distingue de 8.4, que evalúa los servicios de información publicados en la PIDE. | N76: Se espera que el catálogo sea un pilar para el intercambio de datos entre instituciones y con terceros, con APIs RESTful Gubernamentales estandarizadas y seguras. La mejora implica crear y documentar el catálogo, más allá de tener APIs desarrolladas de forma aislada. Ejemplo: La entidad publica un catálogo de 10 APIs documentadas, con ejemplos de uso, que permiten a desarrolladores externos consumir sus datos abiertos de forma masiva.

Sheet Hoja de Puntajes
A1: Dimensión | B1: N° preguntas | C1: N° respondidas (aplicables) | D1: Promedio de la dimensión | E1: Nivel de madurez
A2: D1. ESTRATEGIA DE GOBIERNO DE DATOS | B2: 8 | C2: =COUNT('Matriz de Evaluación'!L2:L9) -> 0 | D2: =IFERROR(AVERAGE('Matriz de Evaluación'!L2:L9),"") | E2: =IF(D2="","",CHOOSE(MIN(MAX(FLOOR(D2,1),0),5)+1,"No iniciado","Inicial","En desarrollo","Definido","Logrado","Optimizado"))
A3: D2. VIABILIDAD FINANCIERA | B3: 5 | C3: =COUNT('Matriz de Evaluación'!L10:L14) -> 0 | D3: =IFERROR(AVERAGE('Matriz de Evaluación'!L10:L14),"") | E3: =IF(D3="","",CHOOSE(MIN(MAX(FLOOR(D3,1),0),5)+1,"No iniciado","Inicial","En desarrollo","Definido","Logrado","Optimizado"))
A4: D3. ORGANIZACIÓN Y CULTURA DE DATOS | B4: 16 | C4: =COUNT('Matriz de Evaluación'!L15:L30) -> 0 | D4: =IFERROR(AVERAGE('Matriz de Evaluación'!L15:L30),"") | E4: =IF(D4="","",CHOOSE(MIN(MAX(FLOOR(D4,1),0),5)+1,"No iniciado","Inicial","En desarrollo","Definido","Logrado","Optimizado"))
A5: D4. ARQUITECTURA DE DATOS | B5: 12 | C5: =COUNT('Matriz de Evaluación'!L31:L42) -> 0 | D5: =IFERROR(AVERAGE('Matriz de Evaluación'!L31:L42),"") | E5: =IF(D5="","",CHOOSE(MIN(MAX(FLOOR(D5,1),0),5)+1,"No iniciado","Inicial","En desarrollo","Definido","Logrado","Optimizado"))
A6: D5. CALIDAD DE DATOS | B6: 9 | C6: =COUNT('Matriz de Evaluación'!L43:L51) -> 0 | D6: =IFERROR(AVERAGE('Matriz de Evaluación'!L43:L51),"") | E6: =IF(D6="","",CHOOSE(MIN(MAX(FLOOR(D6,1),0),5)+1,"No iniciado","Inicial","En desarrollo","Definido","Logrado","Optimizado"))
A7: D6. SEGURIDAD DE DATOS | B7: 9 | C7: =COUNT('Matriz de Evaluación'!L52:L60) -> 0 | D7: =IFERROR(AVERAGE('Matriz de Evaluación'!L52:L60),"") | E7: =IF(D7="","",CHOOSE(MIN(MAX(FLOOR(D7,1),0),5)+1,"No iniciado","Inicial","En desarrollo","Definido","Logrado","Optimizado"))
A8: D7. INFRAESTRUCTURA TECNOLÓGICA Y OPERACIONES DE DATOS | B8: 10 | C8: =COUNT('Matriz de Evaluación'!L61:L70) -> 0 | D8: =IFERROR(AVERAGE('Matriz de Evaluación'!L61:L70),"") | E8: =IF(D8="","",CHOOSE(MIN(MAX(FLOOR(D8,1),0),5)+1,"No iniciado","Inicial","En desarrollo","Definido","Logrado","Optimizado"))
A9: D8. INTEROPERABILIDAD Y DATOS ABIERTOS | B9: 6 | C9: =COUNT('Matriz de Evaluación'!L71:L76) -> 0 | D9: =IFERROR(AVERAGE('Matriz de Evaluación'!L71:L76),"") | E9: =IF(D9="","",CHOOSE(MIN(MAX(FLOOR(D9,1),0),5)+1,"No iniciado","Inicial","En desarrollo","Definido","Logrado","Optimizado"))
A11: PUNTAJE FINAL (promedio de las 8 dimensiones) | D11: =IFERROR(AVERAGE(D2,D3,D4,D5,D6,D7,D8,D9),"") | E11: =IF(D11="","",CHOOSE(MIN(MAX(FLOOR(D11,1),0),5)+1,"No iniciado","Inicial","En desarrollo","Definido","Logrado","Optimizado"))
A13: Nota metodológica: el promedio de cada dimensión y el Puntaje Final excluyen automáticamente del denominador las preguntas marcadas "NA" y las no respondidas (la función AVERAGE de Excel/LibreOffice ignora texto y celdas vacías). Si una dimensión no tiene ninguna respuesta numérica registrada, su promedio y nivel se muestran en blanco hasta que se complete al menos una respuesta.
